gdbundle_example/__init__.py
gdbundle_example/gdb_loader.py
gdbundle_example/lldb_loader.py
gdbundle_example/scripts/example_gdb.gdb
gdbundle_example/scripts/example_gdb.py
gdbundle_example/scripts/example_lldb.py
gdbundle_example-0.0.2.dist-info/WHEEL
gdbundle_example-0.0.2.dist-info/METADATA
gdbundle_example-0.0.2.dist-info/RECORD
